{
  "id": "2972460",
  "name": "xcz",
  "font_family": "iconfont",
  "css_prefix_text": "icon-",
  "description": "",
  "glyphs": [
    {
      "icon_id": "22437208",
      "name": "mail_163",
      "font_class": "mail_163",
      "unicode": "e616",
      "unicode_decimal": 58902
    },
    {
      "icon_id": "902571",
      "name": "精选特卖",
      "font_class": "temai",
      "unicode": "e675",
      "unicode_decimal": 58997
    },
    {
      "icon_id": "1988572",
      "name": "icon-weixin",
      "font_class": "weixin",
      "unicode": "e666",
      "unicode_decimal": 58982
    }
  ]
}
